{
    "run_1": {
        "network": {
            "model": "base_cnn",
            "activation": "softmax"
        },
        "test_size": 0.20,
        "shuffle": true,
        "batch_size": 32,
        "epochs": 50
    },
     "run_2": {
        "network": {
            "model": "base_cnn",
            "activation": "softmax"
        },
           "augmentation": {
            "rotate_random_25": 2,
            "flip_left_right": true
        },
        "test_size": 0.20,
        "shuffle": true,
        "batch_size": 32,
        "epochs": 50
    },
    "run_3": {
        "network": {
            "model": "base_cnn",
            "activation": "softmax"
        },
           "augmentation": {
            "rotate_random_25": 2,
            "blur": 2,
            "flip_left_right": true
        },
        "test_size": 0.20,
        "shuffle": true,
        "batch_size": 32,
        "epochs": 50
    }
}